README
setup.py
daydreamer/__init__.py
daydreamer/core/__init__.py
daydreamer/core/lang.py
daydreamer/core/urlresolvers.py
daydreamer/core/handlers/__init__.py
daydreamer/core/handlers/base.py
daydreamer/core/handlers/wsgi.py
daydreamer/models/__init__.py
daydreamer/test/__init__.py
daydreamer/test/base.py
daydreamer/test/client.py
daydreamer/test/context.py
daydreamer/test/cookies.py
daydreamer/test/handler.py
daydreamer/test/headers.py
daydreamer/test/messages.py
daydreamer/test/redirects.py
daydreamer/test/requests.py
daydreamer/test/testcases.py
daydreamer/test/views/__init__.py
daydreamer/test/views/base.py
daydreamer/test/views/client.py
daydreamer/test/views/handler.py
daydreamer/test/views/redirects.py
daydreamer/test/views/testcases.py
daydreamer/test/views/views.py
daydreamer/test/views/generic/__init__.py
daydreamer/test/views/generic/base.py
daydreamer/test/views/generic/testcases.py
daydreamer/tests/__init__.py
daydreamer/tests/views/__init__.py
daydreamer/tests/views/behaviors/__init__.py
daydreamer/tests/views/behaviors/auth/__init__.py
daydreamer/tests/views/behaviors/auth/base.py
daydreamer/tests/views/behaviors/auth/tests.py
daydreamer/tests/views/behaviors/cache/__init__.py
daydreamer/tests/views/behaviors/cache/base.py
daydreamer/tests/views/behaviors/cache/tests.py
daydreamer/tests/views/behaviors/clickjacking/__init__.py
daydreamer/tests/views/behaviors/clickjacking/base.py
daydreamer/tests/views/behaviors/clickjacking/tests.py
daydreamer/tests/views/behaviors/csrf/__init__.py
daydreamer/tests/views/behaviors/csrf/base.py
daydreamer/tests/views/behaviors/csrf/client.py
daydreamer/tests/views/behaviors/csrf/tests.py
daydreamer/tests/views/behaviors/debug/__init__.py
daydreamer/tests/views/behaviors/debug/base.py
daydreamer/tests/views/behaviors/debug/tests.py
daydreamer/tests/views/behaviors/gzip/__init__.py
daydreamer/tests/views/behaviors/gzip/base.py
daydreamer/tests/views/behaviors/gzip/tests.py
django_daydreamer.egg-info/PKG-INFO
django_daydreamer.egg-info/SOURCES.txt
django_daydreamer.egg-info/dependency_links.txt
django_daydreamer.egg-info/requires.txt
django_daydreamer.egg-info/top_level.txt