Metadata-Version: 1.1
Name: django-daydreamer
Version: 0.0.2a
Summary: A Django class-based view utility library
Home-page: https://github.com/skibblenybbles/django-daydreamer
Author: Mike Kibbel
Author-email: mkibbel@gmail.com
License: MIT License
Platform: OS Independent
Classifier: Development Status :: 3 - Alpha
Classifier: Environment :: Web Environment
Classifier: Framework :: Django
Classifier: Intended Audience :: Developers
Classifier: License :: OSI Approved :: MIT License
Classifier: Natural Language :: English
Classifier: Operating System :: OS Independent
Classifier: Programming Language :: Python
Classifier: Topic :: Software Development :: Libraries :: Application Frameworks
Classifier: Topic :: Software Development :: Libraries :: Python Modules
Classifier: Topic :: Utilities
